README.rst
setup.py
nameko_sqlalchemy/__init__.py
nameko_sqlalchemy/database.py
nameko_sqlalchemy/database_session.py
nameko_sqlalchemy/pytest_fixtures.py
nameko_sqlalchemy/transaction_retry.py
nameko_sqlalchemy.egg-info/PKG-INFO
nameko_sqlalchemy.egg-info/SOURCES.txt
nameko_sqlalchemy.egg-info/dependency_links.txt
nameko_sqlalchemy.egg-info/entry_points.txt
nameko_sqlalchemy.egg-info/requires.txt
nameko_sqlalchemy.egg-info/top_level.txt
nameko_sqlalchemy.egg-info/zip-safe
test/test_database.py
test/test_database_session.py
test/test_pytest_fixtures.py
test/test_transaction_retry.py